generate_source/__init__.py
generate_source/generate_schema.py
generate_source/generate_source.py
ipybootstrapvue/Events.py
ipybootstrapvue/__init__.py
ipybootstrapvue/_version.py
ipybootstrapvue/generated/Alert.py
ipybootstrapvue/generated/Badge.py
ipybootstrapvue/generated/Breadcrumb.py
ipybootstrapvue/generated/BreadcrumbItem.py
ipybootstrapvue/generated/BreadcrumbLink.py
ipybootstrapvue/generated/Btn.py
ipybootstrapvue/generated/BtnClose.py
ipybootstrapvue/generated/BtnGroup.py
ipybootstrapvue/generated/BtnToolbar.py
ipybootstrapvue/generated/Button.py
ipybootstrapvue/generated/ButtonClose.py
ipybootstrapvue/generated/ButtonGroup.py
ipybootstrapvue/generated/ButtonToolbar.py
ipybootstrapvue/generated/Card.py
ipybootstrapvue/generated/CardBody.py
ipybootstrapvue/generated/CardFooter.py
ipybootstrapvue/generated/CardGroup.py
ipybootstrapvue/generated/CardHeader.py
ipybootstrapvue/generated/CardImg.py
ipybootstrapvue/generated/CardImgLazy.py
ipybootstrapvue/generated/CardSubTitle.py
ipybootstrapvue/generated/CardText.py
ipybootstrapvue/generated/CardTitle.py
ipybootstrapvue/generated/Carousel.py
ipybootstrapvue/generated/CarouselSlide.py
ipybootstrapvue/generated/Check.py
ipybootstrapvue/generated/CheckGroup.py
ipybootstrapvue/generated/Checkbox.py
ipybootstrapvue/generated/CheckboxGroup.py
ipybootstrapvue/generated/Col.py
ipybootstrapvue/generated/Collapse.py
ipybootstrapvue/generated/Container.py
ipybootstrapvue/generated/Datalist.py
ipybootstrapvue/generated/Dd.py
ipybootstrapvue/generated/DdDivider.py
ipybootstrapvue/generated/DdForm.py
ipybootstrapvue/generated/DdGroup.py
ipybootstrapvue/generated/DdHeader.py
ipybootstrapvue/generated/DdItem.py
ipybootstrapvue/generated/DdItemBtn.py
ipybootstrapvue/generated/DdItemButton.py
ipybootstrapvue/generated/DdText.py
ipybootstrapvue/generated/Dropdown.py
ipybootstrapvue/generated/DropdownDivider.py
ipybootstrapvue/generated/DropdownForm.py
ipybootstrapvue/generated/DropdownGroup.py
ipybootstrapvue-0.0.1a2.dist-info/LICENSE
ipybootstrapvue-0.0.1a2.dist-info/METADATA
ipybootstrapvue-0.0.1a2.dist-info/WHEEL
ipybootstrapvue-0.0.1a2.dist-info/top_level.txt
ipybootstrapvue-0.0.1a2.dist-info/RECORD
