Metadata-Version: 2.1
Name: ipybootstrapvue
Version: 0.0.1a2
Summary: Jupyter widgets based on bootstrapvue UI components
Home-page: https://github.com/gfournier/ipyvuetify
Author: Mario Buikhuizen, Maarten Breddels
Author-email: mbuikhuizen@gmail.com, maartenbreddels@gmail.com
License: UNKNOWN
Keywords: ipython,jupyter,widgets
Platform: UNKNOWN
Classifier: Development Status :: 4 - Beta
Classifier: Framework :: IPython
Classifier: Intended Audience :: Developers
Classifier: Intended Audience :: Science/Research
Classifier: Topic :: Multimedia :: Graphics
Classifier: Programming Language :: Python :: 2
Classifier: Programming Language :: Python :: 2.7
Classifier: Programming Language :: Python :: 3
Classifier: Programming Language :: Python :: 3.3
Classifier: Programming Language :: Python :: 3.4
Classifier: Programming Language :: Python :: 3.5
Requires-Dist: ipywidgets (>=7.0.0)
